primod/__init__.py
primod/coupled_model.py
primod/metamod.py
primod/ribametamod.py
primod/ribamod.py
primod/typing.py
primod/driver_coupling/__init__.py
primod/driver_coupling/driver_coupling_base.py
primod/driver_coupling/metamod.py
primod/driver_coupling/ribameta.py
primod/driver_coupling/ribamod.py
primod/driver_coupling/util.py
primod/mapping/__init__.py
primod/mapping/mappingbase.py
primod/mapping/node_basin_mapping.py
primod/mapping/node_svat_mapping.py
primod/mapping/rch_svat_mapping.py
primod/mapping/svat_basin_mapping.py
primod/mapping/svat_user_demand_mapping.py
primod/mapping/wel_svat_mapping.py
primod-2024.3.0.dist-info/METADATA
primod-2024.3.0.dist-info/WHEEL
primod-2024.3.0.dist-info/licenses/LICENSE
primod-2024.3.0.dist-info/RECORD
